cmlibs/__init__.py
cmlibs/maths/__init__.py
cmlibs/maths/algorithms.py
cmlibs/maths/octree.py
cmlibs/maths/vectorops.py
cmlibs_maths-0.7.3.dist-info/licenses/LICENSE
cmlibs_maths-0.7.3.dist-info/METADATA
cmlibs_maths-0.7.3.dist-info/WHEEL
cmlibs_maths-0.7.3.dist-info/top_level.txt
cmlibs_maths-0.7.3.dist-info/RECORD
