Metadata-Version: 2.4
Name: cmlibs.maths
Version: 0.7.3
Summary: A collection of math functions and algorithms.
Author-email: Hugh Sorby <h.sorby@auckland.ac.nz>
License-Expression: Apache-2.0
Project-URL: Homepage, https://cmlibs.org
Project-URL: Repository, https://github.com/CMLibs-Python/cmlibs.maths
Keywords: Math,CMLibs,Zinc
Classifier: Programming Language :: Python :: 3
Classifier: Operating System :: OS Independent
Classifier: Topic :: Scientific/Engineering :: Medical Science Apps.
Requires-Python: >=3.8
License-File: LICENSE
Dynamic: license-file
